{
 "plan": {
  "name": "hb650-cav24-phase-trim",
  "kind": "sweep",
  "steps": 9,
  "dwell_s": 2.0,
  "sweeps": [
   {
    "cls": "rf",
    "device": "HB650:CAV24",
    "field": "phase",
    "from": -28.0,
    "to": -8.0
   }
  ],
  "description": "hb650-cav24-phase-trim",
  "restore": true
 },
 "result": {
  "status": "completed",
  "steps": [
   {
    "step": 1,
    "set_values": [
     -28.0
    ],
    "transmission": 0.9955098005914705,
    "w_tof": 798.9076293945312,
    "worst_blm": 54.64413833618164,
    "i_out_ma": 1.7923086881637573,
    "orbit_rms_mm": 1.0316535234451294
   },
   {
    "step": 2,
    "set_values": [
     -25.5
    ],
    "transmission": 0.9955597165603336,
    "w_tof": 799.4856567382812,
    "worst_blm": 57.54722213745117,
    "i_out_ma": 1.7945622205734253,
    "orbit_rms_mm": 1.0325417518615723
   },
   {
    "step": 3,
    "set_values": [
     -23.0
    ],
    "transmission": 0.9955181978131049,
    "w_tof": 799.9187377929687,
    "worst_blm": 57.692779541015625,
    "i_out_ma": 1.7980892658233643,
    "orbit_rms_mm": 1.0329171419143677
   },
   {
    "step": 4,
    "set_values": [
     -20.5
    ],
    "transmission": 0.9955030703704789,
    "w_tof": 799.518798828125,
    "worst_blm": 58.0933952331543,
    "i_out_ma": 1.7934918403625488,
    "orbit_rms_mm": 1.0328998565673828
   },
   {
    "step": 5,
    "set_values": [
     -18.0
    ],
    "transmission": 0.9955746402166781,
    "w_tof": 799.592822265625,
    "worst_blm": 58.420494079589844,
    "i_out_ma": 1.7847687005996704,
    "orbit_rms_mm": 1.0334552526474
   },
   {
    "step": 6,
    "set_values": [
     -15.5
    ],
    "transmission": 0.9955181212477211,
    "w_tof": 800.0341247558594,
    "worst_blm": 56.00568389892578,
    "i_out_ma": 1.7918680906295776,
    "orbit_rms_mm": 1.033658504486084
   },
   {
    "step": 7,
    "set_values": [
     -13.0
    ],
    "transmission": 0.9955488451889606,
    "w_tof": 800.4618286132812,
    "worst_blm": 56.91731643676758,
    "i_out_ma": 1.7960028648376465,
    "orbit_rms_mm": 1.0344982147216797
   },
   {
    "step": 8,
    "set_values": [
     -10.5
    ],
    "transmission": 0.995567887117685,
    "w_tof": 800.559814453125,
    "worst_blm": 58.72844314575195,
    "i_out_ma": 1.8137017488479614,
    "orbit_rms_mm": 1.0351738929748535
   },
   {
    "step": 9,
    "set_values": [
     -8.0
    ],
    "transmission": 0.9954354301220689,
    "w_tof": 800.812255859375,
    "worst_blm": 55.01438903808594,
    "i_out_ma": 1.805537462234497,
    "orbit_rms_mm": 1.03536057472229
   }
  ],
  "t_end": 1783197682.8016217
 }
}