{
 "plan": {
  "name": "c4-quad-btlq2",
  "autotune": true,
  "sweeps": [
   {
    "cls": "magnet",
    "device": "BTL:Q2",
    "field": "current",
    "from": -86.665814,
    "to": -92.026586
   }
  ],
  "kind": "sweep",
  "description": "c4-quad-btlq2",
  "steps": 7,
  "dwell_s": 2.0,
  "restore": true
 },
 "result": {
  "status": "completed",
  "steps": [
   {
    "step": 1,
    "rf_det_rms_hz": 3.24,
    "emit_x_um": 0.23695997893810272,
    "emit_y_um": 0.3292427062988281,
    "set_values": [
     -86.665814
    ],
    "transmission": 0.9954305730380869,
    "w_tof": 800.2095886230469,
    "worst_blm": 4.7867045402526855,
    "i_out_ma": 1.9891998767852783,
    "orbit_rms_mm": 0.19115719199180603
   },
   {
    "step": 2,
    "rf_det_rms_hz": 3.24,
    "emit_x_um": 0.23704420030117035,
    "emit_y_um": 0.32914215326309204,
    "set_values": [
     -87.559276
    ],
    "transmission": 0.9954299616943142,
    "w_tof": 800.1821594238281,
    "worst_blm": 5.060474395751953,
    "i_out_ma": 1.9931108951568604,
    "orbit_rms_mm": 0.1907610446214676
   },
   {
    "step": 3,
    "rf_det_rms_hz": 3.24,
    "emit_x_um": 0.2370227426290512,
    "emit_y_um": 0.32905295491218567,
    "set_values": [
     -88.452738
    ],
    "transmission": 0.9954303281042032,
    "w_tof": 799.90849609375,
    "worst_blm": 4.901580333709717,
    "i_out_ma": 1.990931749343872,
    "orbit_rms_mm": 0.19085891544818878
   },
   {
    "step": 4,
    "rf_det_rms_hz": 3.24,
    "emit_x_um": 0.23701660335063934,
    "emit_y_um": 0.32928770780563354,
    "set_values": [
     -89.3462
    ],
    "transmission": 0.9954306315740659,
    "w_tof": 799.9650390625,
    "worst_blm": 4.800262451171875,
    "i_out_ma": 1.996565818786621,
    "orbit_rms_mm": 0.1908942312002182
   },
   {
    "step": 5,
    "rf_det_rms_hz": 3.24,
    "emit_x_um": 0.23701660335063934,
    "emit_y_um": 0.32928770780563354,
    "set_values": [
     -90.239662
    ],
    "transmission": 0.9954303161879453,
    "w_tof": 799.7268981933594,
    "worst_blm": 4.799604892730713,
    "i_out_ma": 1.9934868812561035,
    "orbit_rms_mm": 0.19117464125156403
   },
   {
    "step": 6,
    "rf_det_rms_hz": 3.24,
    "emit_x_um": 0.2369864284992218,
    "emit_y_um": 0.32908958196640015,
    "set_values": [
     -91.133124
    ],
    "transmission": 0.9954302654313893,
    "w_tof": 799.9383483886719,
    "worst_blm": 4.842690467834473,
    "i_out_ma": 1.9965355396270752,
    "orbit_rms_mm": 0.19122974574565887
   },
   {
    "step": 7,
    "rf_det_rms_hz": 3.24,
    "emit_x_um": 0.23694032430648804,
    "emit_y_um": 0.329202800989151,
    "set_values": [
     -92.026586
    ],
    "transmission": 0.9954299708641142,
    "w_tof": 799.7869812011719,
    "worst_blm": 4.926461696624756,
    "i_out_ma": 1.9939824342727661,
    "orbit_rms_mm": 0.19096821546554565
   }
  ],
  "t_end": 1783300580.1583433
 }
}