{
 "plan": {
  "name": "c4-ph-hb650cav2",
  "autotune": true,
  "sweeps": [
   {
    "cls": "rf",
    "device": "HB650:CAV2",
    "field": "phase",
    "from": -23.0,
    "to": -13.0
   }
  ],
  "kind": "sweep",
  "description": "c4-ph-hb650cav2",
  "steps": 7,
  "dwell_s": 2.0,
  "restore": true
 },
 "result": {
  "status": "completed",
  "steps": [
   {
    "step": 1,
    "rf_det_rms_hz": 3.24,
    "emit_x_um": 0.23691701889038086,
    "emit_y_um": 0.3290737271308899,
    "set_values": [
     -23.0
    ],
    "transmission": 0.995429535836623,
    "w_tof": 800.0361511230469,
    "worst_blm": 4.975119590759277,
    "i_out_ma": 1.9947584867477417,
    "orbit_rms_mm": 0.19143803417682648
   },
   {
    "step": 2,
    "rf_det_rms_hz": 3.24,
    "emit_x_um": 0.23698996007442474,
    "emit_y_um": 0.3290015459060669,
    "set_values": [
     -21.333333333333332
    ],
    "transmission": 0.995430909008791,
    "w_tof": 799.9544311523438,
    "worst_blm": 4.8290252685546875,
    "i_out_ma": 1.9919631481170654,
    "orbit_rms_mm": 0.1907360553741455
   },
   {
    "step": 3,
    "rf_det_rms_hz": 3.24,
    "emit_x_um": 0.23696698248386383,
    "emit_y_um": 0.32924365997314453,
    "set_values": [
     -19.666666666666668
    ],
    "transmission": 0.9954301885951906,
    "w_tof": 800.5426818847657,
    "worst_blm": 4.945608139038086,
    "i_out_ma": 1.9841639995574951,
    "orbit_rms_mm": 0.19124405086040497
   },
   {
    "step": 4,
    "rf_det_rms_hz": 3.24,
    "emit_x_um": 0.23693245649337769,
    "emit_y_um": 0.3290402293205261,
    "set_values": [
     -18.0
    ],
    "transmission": 0.9954306659209076,
    "w_tof": 799.8380737304688,
    "worst_blm": 4.893869400024414,
    "i_out_ma": 1.9944815635681152,
    "orbit_rms_mm": 0.19062697887420654
   },
   {
    "step": 5,
    "rf_det_rms_hz": 3.24,
    "emit_x_um": 0.23698516190052032,
    "emit_y_um": 0.32911938428878784,
    "set_values": [
     -16.333333333333336
    ],
    "transmission": 0.9954297077380351,
    "w_tof": 800.116943359375,
    "worst_blm": 4.958051681518555,
    "i_out_ma": 1.9963496923446655,
    "orbit_rms_mm": 0.19112634658813477
   },
   {
    "step": 6,
    "rf_det_rms_hz": 3.24,
    "emit_x_um": 0.2370031625032425,
    "emit_y_um": 0.32906708121299744,
    "set_values": [
     -14.666666666666666
    ],
    "transmission": 0.9954310543043805,
    "w_tof": 800.2327514648438,
    "worst_blm": 4.914751052856445,
    "i_out_ma": 1.9910953044891357,
    "orbit_rms_mm": 0.1907988041639328
   },
   {
    "step": 7,
    "rf_det_rms_hz": 3.24,
    "emit_x_um": 0.23704653978347778,
    "emit_y_um": 0.32903581857681274,
    "set_values": [
     -13.0
    ],
    "transmission": 0.9954304019251337,
    "w_tof": 800.0202575683594,
    "worst_blm": 5.116242408752441,
    "i_out_ma": 2.008655548095703,
    "orbit_rms_mm": 0.19088433682918549
   }
  ],
  "t_end": 1783299256.1594653
 }
}