{
 "plan": {
  "name": "c4-corr-btlc6-y",
  "sweeps": [
   {
    "cls": "magnet",
    "device": "BTL:C6",
    "field": "current_y",
    "from": -0.5,
    "to": 0.5
   }
  ],
  "kind": "sweep",
  "description": "c4-corr-btlc6-y",
  "steps": 7,
  "dwell_s": 2.0,
  "restore": true
 },
 "result": {
  "status": "completed",
  "steps": [
   {
    "step": 1,
    "rf_det_rms_hz": 3.24,
    "emit_x_um": 0.23702427744865417,
    "emit_y_um": 0.3290996849536896,
    "set_values": [
     -0.5
    ],
    "transmission": 0.9954300454305147,
    "w_tof": 800.4322937011718,
    "worst_blm": 4.993083953857422,
    "i_out_ma": 1.9964094161987305,
    "orbit_rms_mm": 0.1997707486152649
   },
   {
    "step": 2,
    "rf_det_rms_hz": 3.24,
    "emit_x_um": 0.23703765869140625,
    "emit_y_um": 0.3292492628097534,
    "set_values": [
     -0.33333333333333337
    ],
    "transmission": 0.9954306345019266,
    "w_tof": 799.6769409179688,
    "worst_blm": 5.060686111450195,
    "i_out_ma": 1.9869626760482788,
    "orbit_rms_mm": 0.19608871638774872
   },
   {
    "step": 3,
    "rf_det_rms_hz": 3.24,
    "emit_x_um": 0.23711048066616058,
    "emit_y_um": 0.3292689323425293,
    "set_values": [
     -0.16666666666666669
    ],
    "transmission": 0.9954303376002388,
    "w_tof": 799.7677062988281,
    "worst_blm": 4.943692207336426,
    "i_out_ma": 1.9844576120376587,
    "orbit_rms_mm": 0.19324816763401031
   },
   {
    "step": 4,
    "rf_det_rms_hz": 3.24,
    "emit_x_um": 0.23701269924640656,
    "emit_y_um": 0.3290308117866516,
    "set_values": [
     0.0
    ],
    "transmission": 0.9954303998103469,
    "w_tof": 799.8240112304687,
    "worst_blm": 4.799102783203125,
    "i_out_ma": 1.994696021080017,
    "orbit_rms_mm": 0.19166401028633118
   },
   {
    "step": 5,
    "rf_det_rms_hz": 3.24,
    "emit_x_um": 0.23697660863399506,
    "emit_y_um": 0.3290632963180542,
    "set_values": [
     0.16666666666666663
    ],
    "transmission": 0.9954303785385489,
    "w_tof": 799.8619201660156,
    "worst_blm": 5.057363033294678,
    "i_out_ma": 1.9937183856964111,
    "orbit_rms_mm": 0.190986767411232
   },
   {
    "step": 6,
    "rf_det_rms_hz": 3.24,
    "emit_x_um": 0.2370985597372055,
    "emit_y_um": 0.32914602756500244,
    "set_values": [
     0.33333333333333337
    ],
    "transmission": 0.995430277502584,
    "w_tof": 800.0471313476562,
    "worst_blm": 4.889344215393066,
    "i_out_ma": 1.999025821685791,
    "orbit_rms_mm": 0.1909780353307724
   },
   {
    "step": 7,
    "rf_det_rms_hz": 3.24,
    "emit_x_um": 0.23701594769954681,
    "emit_y_um": 0.32901597023010254,
    "set_values": [
     0.5
    ],
    "transmission": 0.9954306929168046,
    "w_tof": 799.3876281738281,
    "worst_blm": 4.923367023468018,
    "i_out_ma": 1.9994648694992065,
    "orbit_rms_mm": 0.19248749315738678
   }
  ],
  "t_end": 1783301000.1576912
 }
}