{
 "plan": {
  "name": "c3-quad-lb650q10",
  "autotune": true,
  "sweeps": [
   {
    "cls": "magnet",
    "device": "LB650:Q10",
    "field": "current",
    "from": -132.77845,
    "to": -140.99155
   }
  ],
  "kind": "sweep",
  "description": "c3-quad-lb650q10",
  "steps": 7,
  "dwell_s": 2.0,
  "restore": true
 },
 "result": {
  "status": "completed",
  "steps": [
   {
    "step": 1,
    "rf_det_rms_hz": 3.24,
    "emit_x_um": 0.2370300441980362,
    "emit_y_um": 0.3287200927734375,
    "set_values": [
     -132.77845
    ],
    "transmission": 0.9954366747314528,
    "w_tof": 799.7521667480469,
    "worst_blm": 4.749711036682129,
    "i_out_ma": 1.9996626377105713,
    "orbit_rms_mm": 0.19314657151699066
   },
   {
    "step": 2,
    "rf_det_rms_hz": 3.24,
    "emit_x_um": 0.2370300441980362,
    "emit_y_um": 0.3287200927734375,
    "set_values": [
     -134.1473
    ],
    "transmission": 0.9954352914942836,
    "w_tof": 799.803564453125,
    "worst_blm": 4.985594272613525,
    "i_out_ma": 1.984744668006897,
    "orbit_rms_mm": 0.19217197597026825
   },
   {
    "step": 3,
    "rf_det_rms_hz": 3.24,
    "emit_x_um": 0.2370300441980362,
    "emit_y_um": 0.3287200927734375,
    "set_values": [
     -135.51614999999998
    ],
    "transmission": 0.9954341358012566,
    "w_tof": 800.0142883300781,
    "worst_blm": 5.080749988555908,
    "i_out_ma": 1.999051809310913,
    "orbit_rms_mm": 0.19161483645439148
   },
   {
    "step": 4,
    "rf_det_rms_hz": 3.24,
    "emit_x_um": 0.2370300441980362,
    "emit_y_um": 0.3287200927734375,
    "set_values": [
     -136.885
    ],
    "transmission": 0.9954297788399068,
    "w_tof": 799.6394165039062,
    "worst_blm": 4.815814971923828,
    "i_out_ma": 1.9959863424301147,
    "orbit_rms_mm": 0.19122414290905
   },
   {
    "step": 5,
    "rf_det_rms_hz": 3.24,
    "emit_x_um": 0.2370300441980362,
    "emit_y_um": 0.3287200927734375,
    "set_values": [
     -138.25385
    ],
    "transmission": 0.9954243376834547,
    "w_tof": 799.8954528808594,
    "worst_blm": 5.122972011566162,
    "i_out_ma": 1.987868309020996,
    "orbit_rms_mm": 0.19080622494220734
   },
   {
    "step": 6,
    "rf_det_rms_hz": 3.24,
    "emit_x_um": 0.23710425198078156,
    "emit_y_um": 0.32922235131263733,
    "set_values": [
     -139.62269999999998
    ],
    "transmission": 0.9954145050186364,
    "w_tof": 799.9948364257813,
    "worst_blm": 4.862526893615723,
    "i_out_ma": 1.984667420387268,
    "orbit_rms_mm": 0.19053886830806732
   },
   {
    "step": 7,
    "rf_det_rms_hz": 3.24,
    "emit_x_um": 0.23710425198078156,
    "emit_y_um": 0.32922235131263733,
    "set_values": [
     -140.99155
    ],
    "transmission": 0.9953961448154603,
    "w_tof": 799.8438415527344,
    "worst_blm": 4.891005039215088,
    "i_out_ma": 2.0075442790985107,
    "orbit_rms_mm": 0.1908981055021286
   }
  ],
  "t_end": 1783292522.1600494
 }
}